{
	"class" : {
		 },
	"instance" : {
		"baseDirectory" : "jupiter 04/08/2017 00:25",
		"baseDirectory:" : "jupiter 04/08/2017 00:24",
		"baseDirectoryAlias" : "jupiter 04/08/2017 00:25",
		"baseDirectoryAlias:" : "jupiter 04/08/2017 00:24",
		"elFinderScript:commandsConfigurationOn:" : "jupiter 04/06/2017 20:27",
		"elFinderScript:connectorConfigurationOn:" : "jupiter 07/06/2017 22:12",
		"elFinderScriptOn:" : "jupiter 04/06/2017 20:27",
		"renderContentOn:" : "jupiter 04/06/2017 20:27",
		"updateRoot:" : "jupiter 04/06/2017 22:07",
		"volumeGroupName" : "jupiter 04/06/2017 23:57",
		"volumeGroupName:" : "jupiter 04/06/2017 23:57" } }
