{
	"class" : {
		"parent:rows:description:" : "DataCurator 04/03/2017 20:17" },
	"instance" : {
		"batchSize" : "DataCurator 04/03/2017 20:17",
		"defaultShowBordered" : "DataCurator 04/03/2017 20:17",
		"defaultShowHeader" : "DataCurator 04/03/2017 20:17",
		"defaultShowStriped" : "DataCurator 04/03/2017 20:17",
		"defaultSortColumn" : "DataCurator 04/03/2017 20:17",
		"iconSelectorForDescription:" : "DataCurator 04/03/2017 20:17",
		"initialize" : "DataCurator 04/03/2017 20:17",
		"parent" : "DataCurator 04/03/2017 20:17",
		"parent:" : "DataCurator 04/03/2017 20:17",
		"renderColumnsForRow:index:on:" : "jupiter 04/06/2017 14:55",
		"renderContentOn:" : "DataCurator 04/03/2017 20:17",
		"renderIconForRow:index:on:" : "DataCurator 04/03/2017 20:17",
		"renderItem:index:on:" : "DataCurator 04/03/2017 20:17",
		"renderLabelsForRow:index:on:" : "DataCurator 04/03/2017 20:17",
		"renderTableBodyOn:" : "DataCurator 04/03/2017 20:17",
		"renderTableOn:" : "DataCurator 04/03/2017 20:17",
		"rowClass" : "DataCurator 04/03/2017 20:17",
		"rows:" : "DataCurator 04/03/2017 20:17",
		"selectedItems" : "DataCurator 04/03/2017 20:17",
		"selectedItems:" : "DataCurator 04/03/2017 20:17" } }
